{".class": "MypyFile", "_fullname": "import", "is_partial_stub_package": false, "is_stub": false, "names": {".class": "SymbolTable", "TfidfVectorizer": {".class": "SymbolTableNode", "kind": "Gdef", "node": {".class": "Var", "flags": ["is_suppressed_import"], "fullname": "import.TfidfVectorizer", "name": "TfidfVectorizer", "type": {".class": "AnyType", "missing_import_name": "import.TfidfVectorizer", "source_any": null, "type_of_any": 3}}}, "__doc__": {".class": "SymbolTableNode", "kind": "Gdef", "node": {".class": "Var", "flags": [], "fullname": "import.__doc__", "name": "__doc__", "type": "builtins.str"}}, "__file__": {".class": "SymbolTableNode", "kind": "Gdef", "node": {".class": "Var", "flags": [], "fullname": "import.__file__", "name": "__file__", "type": "builtins.str"}}, "__name__": {".class": "SymbolTableNode", "kind": "Gdef", "node": {".class": "Var", "flags": [], "fullname": "import.__name__", "name": "__name__", "type": "builtins.str"}}, "__package__": {".class": "SymbolTableNode", "kind": "Gdef", "node": {".class": "Var", "flags": [], "fullname": "import.__package__", "name": "__package__", "type": "builtins.str"}}, "csv": {".class": "SymbolTableNode", "cross_ref": "csv", "kind": "Gdef"}, "f": {".class": "SymbolTableNode", "kind": "Gdef", "node": {".class": "Var", "flags": [], "fullname": "import.f", "name": "f", "type": "typing.TextIO"}}, "np": {".class": "SymbolTableNode", "kind": "Gdef", "node": {".class": "Var", "flags": ["is_suppressed_import"], "fullname": "import.np", "name": "np", "type": {".class": "AnyType", "missing_import_name": "import.np", "source_any": null, "type_of_any": 3}}}}, "path": "/Users/aaronbu/Documents/cs4300sp2019-acb256_kt474_az246_nbb42/import.py"}